arg_dispatch/__init__.py
arg_dispatch/_arg_dispatch.py
arg_dispatch/_registry.py
arg_dispatch-0.1.3.dist-info/LICENSE
arg_dispatch-0.1.3.dist-info/WHEEL
arg_dispatch-0.1.3.dist-info/METADATA
arg_dispatch-0.1.3.dist-info/RECORD
