Metadata-Version: 2.1
Name: arg-dispatch
Version: 0.1.3
Summary: function can be dispatched by its arguments
Home-page: https://github.com/zen-xu/arg_dispatch
License: GPL-3.0
Keywords: dispatch
Author: zen-xu
Author-email: zen-xu@outlook.com
Requires-Python: >=3.6,<4.0
Classifier: Intended Audience :: Developers
Classifier: License :: OSI Approved :: GNU General Public License v3 (GPLv3)
Classifier: Operating System :: OS Independent
Classifier: Programming Language :: Python
Classifier: Programming Language :: Python :: 3
Classifier: Programming Language :: Python :: 3.6
Classifier: Programming Language :: Python :: 3.7
Project-URL: Repository, https://github.com/zen-xu/arg_dispatch
